versatility.py
versatility-1.0.1.dist-info/METADATA
versatility-1.0.1.dist-info/WHEEL
versatility-1.0.1.dist-info/top_level.txt
versatility-1.0.1.dist-info/RECORD
