Metadata-Version: 2.1
Name: versatility
Version: 1.0.1
Summary: Versatility - find how closely a node in a graph is associated with a community
Home-page: https://github.com/mwshinn/versatility
Author: Max Shinn
Author-email: maxwell.shinn@yale.edu
Maintainer: Max Shinn
Maintainer-email: maxwell.shinn@yale.edu
License: GPL3
Platform: UNKNOWN
Classifier: Development Status :: 4 - Beta
Classifier: Intended Audience :: Science/Research
Classifier: License :: OSI Approved :: GNU General Public License v3 (GPLv3)
Classifier: Programming Language :: Python :: 3
Classifier: Topic :: Scientific/Engineering
Classifier: Topic :: Scientific/Engineering :: Physics
Classifier: Topic :: Scientific/Engineering :: Medical Science Apps.
Classifier: Topic :: Scientific/Engineering :: Bio-Informatics
Requires-Python: >=3.5
Requires-Dist: numpy
Requires-Dist: scipy
Requires-Dist: matplotlib
Requires-Dist: bctpy
Requires-Dist: networkx
